wtforms_components/__init__.py
wtforms_components/validators.py
wtforms_components/widgets.py
wtforms_components/fields/__init__.py
wtforms_components/fields/ajax.py
wtforms_components/fields/color.py
wtforms_components/fields/html5.py
wtforms_components/fields/interval.py
wtforms_components/fields/json_field.py
wtforms_components/fields/passive_hidden.py
wtforms_components/fields/select.py
wtforms_components/fields/select_multiple.py
wtforms_components/fields/split_date_time.py
wtforms_components/fields/time.py
WTForms_Components-0.11.0.dist-info/LICENSE
WTForms_Components-0.11.0.dist-info/METADATA
WTForms_Components-0.11.0.dist-info/WHEEL
WTForms_Components-0.11.0.dist-info/top_level.txt
WTForms_Components-0.11.0.dist-info/RECORD
