Metadata-Version: 2.1
Name: WTForms-Components
Version: 0.11.0
Summary: Additional fields, validators and widgets for WTForms.
Home-page: https://github.com/kvesteri/wtforms-components
Author: Konsta Vesterinen
Author-email: konsta@fastmonkeys.com
License: BSD
Platform: any
Classifier: Environment :: Web Environment
Classifier: Intended Audience :: Developers
Classifier: License :: OSI Approved :: BSD License
Classifier: Operating System :: OS Independent
Classifier: Programming Language :: Python
Classifier: Programming Language :: Python :: 3
Classifier: Programming Language :: Python :: 3.9
Classifier: Programming Language :: Python :: 3.10
Classifier: Programming Language :: Python :: 3.11
Classifier: Programming Language :: Python :: 3.12
Classifier: Programming Language :: Python :: 3 :: Only
Classifier: Programming Language :: Python :: Implementation :: CPython
Classifier: Programming Language :: Python :: Implementation :: PyPy
Classifier: Topic :: Internet :: WWW/HTTP :: Dynamic Content
Classifier: Topic :: Software Development :: Libraries :: Python Modules
Requires-Python: >=3.9
License-File: LICENSE
Requires-Dist: WTForms>=3.1.0
Requires-Dist: validators>=0.21
Requires-Dist: intervals>=0.6.0
Requires-Dist: MarkupSafe>=1.0.0
Provides-Extra: test
Requires-Dist: pytest>=2.2.3; extra == "test"
Requires-Dist: flexmock>=0.9.7; extra == "test"
Requires-Dist: ruff==0.7.3; extra == "test"
Requires-Dist: WTForms-Test>=0.1.1; extra == "test"
Requires-Dist: colour>=0.0.4; extra == "test"
Requires-Dist: python-dateutil; extra == "test"
Provides-Extra: color
Requires-Dist: colour>=0.0.4; extra == "color"
Provides-Extra: ipaddress
Provides-Extra: timezone
Requires-Dist: python-dateutil; extra == "timezone"
